pokemon_yeet/__init__.py
pokemon_yeet/constants.py
pokemon_yeet/pokemon.py
pokemon_yeet/utilities.py
pokemon_yeet_2ndbillingcycle-0.0.6.dist-info/entry_points.txt
pokemon_yeet_2ndbillingcycle-0.0.6.dist-info/WHEEL
pokemon_yeet_2ndbillingcycle-0.0.6.dist-info/METADATA
pokemon_yeet_2ndbillingcycle-0.0.6.dist-info/RECORD
