Metadata-Version: 2.1
Name: pokemon-yeet-2ndbillingcycle
Version: 0.0.6
Summary: An auto battling Pokémon cli game
Home-page: https://github.com/2ndbillingcycle/pokemon_yeet
License: UNKNOWN
Author: 2ndBillingCycle
Author-email: 2nd+github@2ndbillingcycle.stream
Requires-Python: >=3.7,<4
Classifier: Programming Language :: Python :: 3 :: Only
Classifier: Programming Language :: Python :: 3
Classifier: Topic :: Games/Entertainment
Requires-Dist: requests >= 2.25.1
Requires-Dist: appdirs >= 1.4.4
